README.md
setup.cfg
setup.py
pyfplapi/__init__.py
python_fpl_api.egg-info/PKG-INFO
python_fpl_api.egg-info/SOURCES.txt
python_fpl_api.egg-info/dependency_links.txt
python_fpl_api.egg-info/requires.txt
python_fpl_api.egg-info/top_level.txt
python_fpl_api.egg-info/zip-safe