Metadata-Version: 1.1
Name: python-fpl-api
Version: 0.0.3
Summary: Python API for accessing energy usage data from Florida Power & Light.
Home-page: https://github.com/Klathmon/python-fpl-api
Author: Gregory Benner
Author-email: gregbenner1@gmail.com
License: MIT
Download-URL: https://github.com/Klathmon/python-fpl-api/archive/0.0.1.tar.gz
Platform: UNKNOWN
